liwc_trie/__init__.py
liwc_trie/__main__.py
liwc_trie/dicx.py
liwc_trie/py.typed
liwc_trie/trie.py
liwc_trie-0.1.0.dist-info/entry_points.txt
liwc_trie-0.1.0.dist-info/LICENSE
liwc_trie-0.1.0.dist-info/WHEEL
liwc_trie-0.1.0.dist-info/METADATA
liwc_trie-0.1.0.dist-info/RECORD
