Metadata-Version: 2.1
Name: liwc-trie
Version: 0.1.0
Summary: LIWC Trie
Home-page: https://github.com/garth74/liwc-trie
License: MIT
Author: Garrett M. Shipley
Author-email: garrett.shipley7@gmail.com
Requires-Python: >=3.7,<4.0
Classifier: Development Status :: 4 - Beta
Classifier: License :: OSI Approved :: MIT License
Classifier: Programming Language :: Python :: 3
Classifier: Programming Language :: Python :: 3.10
Classifier: Programming Language :: Python :: 3.7
Classifier: Programming Language :: Python :: 3.8
Classifier: Programming Language :: Python :: 3.9
Requires-Dist: click (>=8.0.1)
Project-URL: Changelog, https://github.com/garth74/liwc-trie/releases
Project-URL: Documentation, https://liwc-trie.readthedocs.io
Project-URL: Repository, https://github.com/garth74/liwc-trie
